[{"id":"1774001525_8968","author":"Mic KLk","restrictions":{"always_attached":{"enabled":false},"job":{"enabled":false,"list":[]},"zone":{"enabled":false,"list":[]},"remove":{"enabled":false,"value":1},"cooldown":{"enabled":false,"value":0}},"desc":"test","icon":"fa-box","name":"test_item","features":[{"type":"Placeable Prop","icon":"fa-box","data":{"name":"prop_paints_can07"}}],"tags":[]},{"id":"1774002318_3750","author":"Mic","restrictions":{"always_attached":{"enabled":false},"job":{"enabled":false,"list":[]},"zone":{"enabled":false,"list":[]},"remove":{"enabled":false,"value":1},"cooldown":{"enabled":false,"value":0}},"desc":"Just a weel","icon":"fa-terminal","name":"Wheel","features":[{"type":"Command","icon":"fa-terminal","data":{"value":"me hola"}}],"tags":[]},{"id":"1774004325_5062","author":"resrse","features":[{"type":"Command","icon":"fa-terminal","data":{"value":"me hola"}}],"desc":"esrre","icon":"fa-terminal","name":"Monkey Mask","tags":[],"restrictions":{"always_attached":{"enabled":false},"job":{"enabled":false,"list":[]},"zone":{"enabled":false,"list":[]},"remove":{"enabled":false,"value":1},"cooldown":{"enabled":false,"value":0}}}]